recombulatorx/__init__.py
recombulatorx/cli.py
recombulatorx/estimate.py
recombulatorx/families.py
recombulatorx/io.py
recombulatorx/likelihood.py
recombulatorx/likelihood_direct.py
recombulatorx/testing.py
recombulatorx/types.py
recombulator_x-1.1.2.dist-info/LICENSE.md
recombulator_x-1.1.2.dist-info/METADATA
recombulator_x-1.1.2.dist-info/WHEEL
recombulator_x-1.1.2.dist-info/entry_points.txt
recombulator_x-1.1.2.dist-info/top_level.txt
recombulator_x-1.1.2.dist-info/RECORD
