Metadata-Version: 2.1
Name: recombulator-x
Version: 1.1.2
Summary: estimation of recombination rates between short tandem repeats (STRs) or other polymorphisms (SNP/indels) along the X chromosome
Home-page: https://serena-aneli.github.io/recombulator-x/
Author: Serena Aneli
Author-email: serena.aneli@unito.it
License: MIT
Classifier: Development Status :: 5 - Production/Stable
Classifier: Environment :: Console
Classifier: Intended Audience :: Science/Research
Classifier: License :: OSI Approved :: MIT License
Classifier: Programming Language :: Python :: 3
Classifier: Topic :: Scientific/Engineering :: Bio-Informatics
Requires-Python: >=3.7
License-File: LICENSE.md
Requires-Dist: numpy (>=1.15.4)
Requires-Dist: scipy (>=1.2.0)
Requires-Dist: networkx (>=2.0)
Requires-Dist: pandas (>=0.23.4)
Provides-Extra: jit
Requires-Dist: numba (>=0.49.0) ; extra == 'jit'
Provides-Extra: plot
Requires-Dist: matplotlib (>=3.0.0) ; extra == 'plot'
